vec2d/graph/__init__.py
vec2d/graph/vector2d_graphics.py
vec2d/math/__init__.py
vec2d/math/vector2d_math.py
vec2d-0.2.3.dist-info/LICENSE
vec2d-0.2.3.dist-info/METADATA
vec2d-0.2.3.dist-info/WHEEL
vec2d-0.2.3.dist-info/RECORD
