Metadata-Version: 2.1
Name: vec2d
Version: 0.2.3
Summary: Maths and Graph functions for vectors on the 2D plane
Home-page: https://github.com/sergiofgonzalez/vec2d
License: MIT
Author: Sergio F. Gonzalez
Author-email: sergio.f.gonzalez@gmail.com
Requires-Python: >=3.10,<4.0
Classifier: License :: OSI Approved :: MIT License
Classifier: Programming Language :: Python :: 3
Classifier: Programming Language :: Python :: 3.10
Classifier: Programming Language :: Python :: 3.11
Classifier: Programming Language :: Python :: 3.12
Requires-Dist: matplotlib (>=3.8.2,<4.0.0)
Requires-Dist: numpy (>=1.26.3,<2.0.0)
Project-URL: Repository, https://github.com/sergiofgonzalez/vec2d
